[
    {
        "cau_hoi": "What is the comparison mavhj",
        "nhan_so": [
            "[1, 0, 12, 0, 0, 0, 0, 0, 0]",
            "[1, 5, 0, 0, 0, 0, 0, 0, 0]"
        ],
        "nhan_chu": [
            "['definition', '', 'comparator ', '', '', '', '', '', '']",
            "['definition', 'bandwith (BW)', '', '', '', '', '', '', '']"
        ],
        "cau_tra_loi": [
            "a comparator is a circuit that compares two analog input voltages and provides a digital output, typically a high or low voltage, indicating which input is larger",
            "The bandwidth (BW) of a comparator refers to the range of frequencies over which the comparator can accurately respond to input signals and produce a valid output"
        ]
    },
    {
        "cau_hoi": "What is comparison circuit",
        "nhan_so": [],
        "nhan_chu": [],
        "cau_tra_loi": []
    },
    {
        "cau_hoi": "What is the comparison mavhj",
        "nhan_so": [
            "[1, 0, 12, 0, 0, 0, 0, 0, 0]",
            "[1, 5, 0, 0, 0, 0, 0, 0, 0]"
        ],
        "nhan_chu": [
            "['definition', '', 'comparator ', '', '', '', '', '', '']",
            "['definition', 'bandwith (BW)', '', '', '', '', '', '', '']"
        ],
        "cau_tra_loi": [
            "a comparator is a circuit that compares two analog input voltages and provides a digital output, typically a high or low voltage, indicating which input is larger",
            "The bandwidth (BW) of a comparator refers to the range of frequencies over which the comparator can accurately respond to input signals and produce a valid output"
        ]
    },
    {
        "cau_hoi": "What is comparison circuit",
        "nhan_so": [],
        "nhan_chu": [],
        "cau_tra_loi": []
    },
    {
        "cau_hoi": "What is comparison",
        "nhan_so": [
            "[1, 0, 12, 0, 0, 0, 0, 0, 0]",
            "[1, 5, 0, 0, 0, 0, 0, 0, 0]"
        ],
        "nhan_chu": [
            "['definition', '', 'comparator ', '', '', '', '', '', '']",
            "['definition', 'bandwith (BW)', '', '', '', '', '', '', '']"
        ],
        "cau_tra_loi": [
            "a comparator is a circuit that compares two analog input voltages and provides a digital output, typically a high or low voltage, indicating which input is larger",
            "The bandwidth (BW) of a comparator refers to the range of frequencies over which the comparator can accurately respond to input signals and produce a valid output"
        ]
    },
    {
        "cau_hoi": "What is comparison circuit",
        "nhan_so": [
            "[9, 0, 12, 1, 0, 0, 0, 0, 0]"
        ],
        "nhan_chu": [
            "['how circuit operation', '', 'comparator ', 'noisy environment', '', '', '', '', '']"
        ],
        "cau_tra_loi": [
            "In a noisy environment, the output of a comparator can experience increased jitter, false switching, and reduced reliability, making it difficult to consistently detect the correct threshold. Noise can cause spurious transitions, widened pulses, and shift the effective threshold voltage."
        ]
    },
    {
        "cau_hoi": "What is the banana",
        "nhan_so": [
            "[1, 0, 12, 0, 0, 0, 0, 0, 0]",
            "[1, 5, 0, 0, 0, 0, 0, 0, 0]"
        ],
        "nhan_chu": [
            "['definition', '', 'comparator ', '', '', '', '', '', '']",
            "['definition', 'bandwith (BW)', '', '', '', '', '', '', '']"
        ],
        "cau_tra_loi": [
            "a comparator is a circuit that compares two analog input voltages and provides a digital output, typically a high or low voltage, indicating which input is larger",
            "The bandwidth (BW) of a comparator refers to the range of frequencies over which the comparator can accurately respond to input signals and produce a valid output"
        ]
    },
    {
        "cau_hoi": "Adhalkdhach;'s Cakcjsacjsacjsacjsa Capcjaskclas",
        "nhan_so": [],
        "nhan_chu": [],
        "cau_tra_loi": [
            "Sorry, I don't have an answer to your question."
        ]
    },
    {
        "cau_hoi": "How does the transformer work",
        "nhan_so": [
            "[9, 0, 12, 3, 0, 0, 0, 0, 0]"
        ],
        "nhan_chu": [
            "['how circuit operation', '', 'comparator ', 'rapid changes', '', '', '', '', '']"
        ],
        "cau_tra_loi": [
            "When a comparator faces rapid changes in input voltage, it experiences propagation delay, which increases with the input rate. Fast inputs may exceed the comparator's slew rate, leading to distortion and reduced accuracy"
        ]
    },
    {
        "cau_hoi": "What comparisons include?",
        "nhan_so": [
            "[1, 0, 12, 0, 0, 0, 0, 0, 0]",
            "[1, 5, 0, 0, 0, 0, 0, 0, 0]"
        ],
        "nhan_chu": [
            "['definition', '', 'comparator ', '', '', '', '', '', '']",
            "['definition', 'bandwith (BW)', '', '', '', '', '', '', '']"
        ],
        "cau_tra_loi": [
            "a comparator is a circuit that compares two analog input voltages and provides a digital output, typically a high or low voltage, indicating which input is larger",
            "The bandwidth (BW) of a comparator refers to the range of frequencies over which the comparator can accurately respond to input signals and produce a valid output"
        ]
    },
    {
        "cau_hoi": "Comparison circuit has any applications in reality",
        "nhan_so": [
            "[17, 0, 12, 0, 0, 0, 0, 0, 0]"
        ],
        "nhan_chu": [
            "['resource, textbook', '', 'comparator ', '', '', '', '', '', '']"
        ],
        "cau_tra_loi": [
            "You can read the book CMOS Analog Circuit Design by Phillip E. Allen, Design of Analog CMOS Integrated Circuits by Razavi, or the book Thiß¦+t kß¦+ IC T¦¦¦íng Tß+¦ by Phß¦ím Nguyß+àn Thanh Loan"
        ]
    },
    {
        "cau_hoi": "I like you",
        "nhan_so": [],
        "nhan_chu": [],
        "cau_tra_loi": [
            "Sorry, I don't have an answer to your question."
        ]
    }
]